imageio/__init__.py
imageio/__main__.py
imageio/freeze.py
imageio/py.typed
imageio/testing.py
imageio/typing.py
imageio/v2.py
imageio/v2.pyi
imageio/v3.py
imageio/v3.pyi
imageio/config/__init__.py
imageio/config/extensions.py
imageio/config/extensions.pyi
imageio/config/plugins.py
imageio/config/plugins.pyi
imageio/core/__init__.py
imageio/core/fetching.py
imageio/core/findlib.py
imageio/core/format.py
imageio/core/format.pyi
imageio/core/imopen.py
imageio/core/imopen.pyi
imageio/core/legacy_plugin_wrapper.py
imageio/core/legacy_plugin_wrapper.pyi
imageio/core/request.py
imageio/core/request.pyi
imageio/core/util.py
imageio/core/v3_plugin_api.py
imageio/plugins/__init__.py
imageio/plugins/_bsdf.py
imageio/plugins/_dicom.py
imageio/plugins/_freeimage.py
imageio/plugins/_swf.py
imageio/plugins/_tifffile.py
imageio/plugins/bsdf.py
imageio/plugins/dicom.py
imageio/plugins/example.py
imageio/plugins/feisem.py
imageio/plugins/ffmpeg.py
imageio/plugins/fits.py
imageio/plugins/freeimage.py
imageio/plugins/freeimagemulti.py
imageio/plugins/gdal.py
imageio/plugins/grab.py
imageio/plugins/lytro.py
imageio/plugins/npz.py
imageio/plugins/opencv.py
imageio/plugins/pillow.py
imageio/plugins/pillow_info.py
imageio/plugins/pillow_legacy.py
imageio/plugins/pillowmulti.py
imageio/plugins/pyav.py
imageio/plugins/rawpy.py
imageio/plugins/simpleitk.py
imageio/plugins/spe.py
imageio/plugins/swf.py
imageio/plugins/tifffile.py
imageio/plugins/tifffile_v3.py
imageio-2.37.0.dist-info/LICENSE
imageio-2.37.0.dist-info/METADATA
imageio-2.37.0.dist-info/WHEEL
imageio-2.37.0.dist-info/entry_points.txt
imageio-2.37.0.dist-info/top_level.txt
imageio-2.37.0.dist-info/RECORD
