Metadata-Version: 2.1
Name: imageio
Version: 2.37.0
Summary: Library for reading and writing a wide range of image, video, scientific, and volumetric data formats.
Home-page: https://github.com/imageio/imageio
Download-URL: http://pypi.python.org/pypi/imageio
Author: imageio contributors
Author-email: almar.klein@gmail.com
License: BSD-2-Clause
Keywords: image video volume imread imwrite io animation ffmpeg
Platform: any
Classifier: Development Status :: 5 - Production/Stable
Classifier: Intended Audience :: Science/Research
Classifier: Intended Audience :: Education
Classifier: Intended Audience :: Developers
Classifier: License :: OSI Approved :: BSD License
Classifier: Operating System :: MacOS :: MacOS X
Classifier: Operating System :: Microsoft :: Windows
Classifier: Operating System :: POSIX
Classifier: Programming Language :: Python :: 3
Classifier: Programming Language :: Python :: 3.9
Classifier: Programming Language :: Python :: 3.10
Classifier: Programming Language :: Python :: 3.11
Classifier: Programming Language :: Python :: 3.12
Classifier: Programming Language :: Python :: 3.13
Classifier: Programming Language :: Python :: 3.14
Provides: imageio
Requires-Python: >=3.9
Provides-Extra: build
Provides-Extra: linting
Provides-Extra: test
Provides-Extra: docs
Provides-Extra: bsdf
Provides-Extra: dicom
Provides-Extra: feisem
Provides-Extra: ffmpeg
Provides-Extra: freeimage
Provides-Extra: lytro
Provides-Extra: numpy
Provides-Extra: pillow-heif
Provides-Extra: pillow
Provides-Extra: pyav
Provides-Extra: simpleitk
Provides-Extra: spe
Provides-Extra: swf
Provides-Extra: tifffile
Provides-Extra: fits
Provides-Extra: rawpy
Provides-Extra: gdal
Provides-Extra: itk
Provides-Extra: full
Provides-Extra: dev
Provides-Extra: all-plugins
Provides-Extra: all-plugins-pypy
License-File: LICENSE
